{
    "meta_properties": {
        "og:site_name": "Fellipe Brito",
        "og:title": "Siga em Frente – [Discografia U2]",
        "og:type": "article",
        "og:description": "[][1]\n\n",
        "og:image": "http://fellipebrito.com/assets/images/header.jpg",
        "article:published_time": "2014-06-26T00:00:00-05:00",
        "article:author": "http://fellipebrito.com/about/",
        "og:url": "http://fellipebrito.com/u2-siga-em-frente/",
        "article:tag": "u2"
    },
    "post_content_markdown": "[![siga-em-frente](/img/posts/2014/06/siga-em-frente-300x178.jpg)][1]\n\nUltimamente, quando me perguntam qual minha banda gospel favorita, eu respondo\nsem pensar: U2!\n\nO engraçado é que eu não ouço em loop, nem sei a discografia completa (isso\nestá mudando). Mas eles são quem eu mais gosto. As letras, a missão, o\nobjetivo… sim, eles são minha banda favorita. Segue aqui um dos exemplos do\nporque disso:\n\n_Você esta fazendo a mala para um lugar, onde nenhum de nós esteve._ _Um lugar\nno qual se tem que acreditar para se ver._ _Foi pra onde você voou, pra longe…\num pássaro de canto numa gaiola aberta_\n\n_Você tem que deixar isso para trás:_ _Tudo o que você produz_ _Tudo o que\nvocê faz_ _Tudo o que você constroe_ _Tudo o que você quebra_ _Tudo o que você\nmede_ _Tudo o que você sente_ _Tudo o que você percebe_ _Tudo o que você\nconspira_ _Tudo o que você veste_ _Tudo o que você vê_ _Tudo o que você cria_\n_Tudo o que você destrói_ *Tudo o que você odeia Tudo o que você raciocina, é\napenas tempo *Tudo isso você pode deixar pra trás**\n\n_O amor não é a mais fácil das coisas, e de todas as bagagens que você pode\ntrazer, ele é tudo o que você não pode deixar para trás._\n\n_E se a escuridão for nos separar, ou se a luz do dia parecer estar muito\nlonge;_ _E se o seu coração de vidro for quebrar ou por um segundo você quiser\nvoltar atrás;_ _Oh, não! Seja forte!!!_\n\n_Siga em frente! Siga em frente!_ _O que você tem eles não podem roubar! Eles\nnão podem nem sentir!_ _O que você conquistou eles não podem negar, Não podem\nvender, nem podem comprar!_ _Siga em frente! Siga em frente! Mantenha-se em\nsegurança por mais esta noite_\n\n_E eu sei que dói, e então o seu coração ele se quebra_ _Você só pode aguentar\naté um certo ponto, mas eu te digo:_ _Siga em frente! Siga em frente!_\n\n[![YouTube\nVideo](http://img.youtube.com/vi/gwKEdFoUB0o/0.jpg)](http://www.youtube.com/watch?v=gwKEdFoUB0o)\n\n"
}